{"propertiesBar":{"properties":[{"name":"About","expanded":true,"children":[]},{"name":"Colors","expanded":true,"children":[]},{"name":"Startup","expanded":true,"children":[]},{"name":"Display","expanded":true,"children":[{"name":"Viewport size","expanded":true,"children":[]}]},{"name":"Advanced","expanded":true,"children":[]},{"name":"Compatibility settings","expanded":true,"children":[]},{"name":"Editor","expanded":true,"children":[]}],"scrollPosition":0},"openTabs":{"active":{"name":"Layout 1","type":"layout"},"open":[{"name":"MainMenu","type":"layout"},{"name":"eMainMenu","type":"eventSheet"},{"name":"Layout 1","type":"layout"},{"name":"Event sheet 1","type":"eventSheet"}]},"previewEffects":true,"previewBrowser":"default","pauseOnUnfocus":false,"projectBar":{"name":"<root>","children":[{"name":"Snake","expanded":true,"children":[{"name":"Layouts","expanded":false,"children":[{"name":"MainMenu","expanded":true,"children":[]},{"name":"Layout 1","expanded":true,"children":[]}]},{"name":"Event sheets","expanded":false,"children":[{"name":"eMainMenu","expanded":true,"children":[]},{"name":"Event sheet 1","expanded":true,"children":[]}]},{"name":"Scripts","expanded":true,"children":[]},{"name":"Object types","expanded":true,"children":[{"name":"Background","expanded":false,"children":[{"name":"AppleTree","expanded":true,"children":[]},{"name":"BG_MainMenu","expanded":true,"children":[]},{"name":"Spr_Darken","expanded":true,"children":[]},{"name":"Spr_FadeIn","expanded":true,"children":[]},{"name":"Spr_FadeOut","expanded":true,"children":[]},{"name":"Spr_FadeOut2","expanded":true,"children":[]},{"name":"TM_Decor","expanded":true,"children":[]},{"name":"TM_Forest","expanded":true,"children":[]},{"name":"TM_Forest2","expanded":true,"children":[]},{"name":"TM_Ground","expanded":true,"children":[]},{"name":"TM_Tree","expanded":true,"children":[]}]},{"name":"GUI","expanded":false,"children":[{"name":"BG_Title","expanded":true,"children":[]},{"name":"Board","expanded":true,"children":[]},{"name":"GUI_PlayBtn","expanded":true,"children":[]},{"name":"GUI_RetryBtn","expanded":true,"children":[]},{"name":"GUI_ReturnBtn","expanded":true,"children":[]},{"name":"Spr_Instruction","expanded":true,"children":[]},{"name":"Spr_Joystick","expanded":true,"children":[]},{"name":"Spr_JoystickBase","expanded":true,"children":[]},{"name":"Spr_Play","expanded":true,"children":[]}]},{"name":"Input","expanded":false,"children":[{"name":"Audio","expanded":true,"children":[]},{"name":"Keyboard","expanded":true,"children":[]},{"name":"LS_SnakeScore","expanded":true,"children":[]},{"name":"TimelineController","expanded":true,"children":[]},{"name":"Touch","expanded":true,"children":[]}]},{"name":"New","expanded":true,"children":[{"name":"Flashes","expanded":true,"children":[]},{"name":"Plants","expanded":true,"children":[]},{"name":"Sprite","expanded":true,"children":[]},{"name":"SpriteFont","expanded":true,"children":[]}]},{"name":"Sprites","expanded":true,"children":[{"name":"Frog_Aggro","expanded":true,"children":[]},{"name":"Frog_BG","expanded":true,"children":[]},{"name":"Frog_Docile","expanded":true,"children":[]},{"name":"Spr_Apple","expanded":true,"children":[]},{"name":"Spr_Banner","expanded":true,"children":[]},{"name":"Spr_InvisibleWall","expanded":true,"children":[]},{"name":"Spr_PowerUp","expanded":true,"children":[]},{"name":"Spr_SnakeHead","expanded":true,"children":[]},{"name":"Spr_SnakeJoint","expanded":true,"children":[]},{"name":"Spr_SnakePart","expanded":true,"children":[]},{"name":"Spr_SnakeTail","expanded":true,"children":[]},{"name":"Spr_SnakeTongue","expanded":true,"children":[]}]},{"name":"Text","expanded":false,"children":[{"name":"Txt_CurrentScore","expanded":true,"children":[]},{"name":"Txt_FullScreen","expanded":true,"children":[]},{"name":"Txt_HighScore","expanded":true,"children":[]},{"name":"Txt_PlusPoint","expanded":true,"children":[]}]}]},{"name":"Families","expanded":true,"children":[]},{"name":"Timelines","expanded":false,"children":[{"name":"Eases","expanded":true,"children":[]},{"name":"Appear","expanded":true,"children":[]},{"name":"AppleFlip","expanded":true,"children":[]}]},{"name":"Flowcharts","expanded":true,"children":[]},{"name":"Sounds","expanded":false,"children":[{"name":"Big Egg collect 1.webm","expanded":true,"children":[]},{"name":"Bubble heavy 2.webm","expanded":true,"children":[]},{"name":"Cancel 1.webm","expanded":true,"children":[]},{"name":"Fruit collect 1.webm","expanded":true,"children":[]}]},{"name":"Music","expanded":false,"children":[{"name":"Home Town (mp3cut.net).webm","expanded":true,"children":[]},{"name":"NODOKA.webm","expanded":true,"children":[]},{"name":"SimpleBattleBGM.webm","expanded":true,"children":[]},{"name":"Theme.webm","expanded":true,"children":[]}]},{"name":"Videos","expanded":true,"children":[]},{"name":"Fonts","expanded":true,"children":[]},{"name":"Icons & screenshots","expanded":false,"children":[{"name":"icon-128.png","expanded":true,"children":[]},{"name":"icon-16.png","expanded":true,"children":[]},{"name":"icon-256.png","expanded":true,"children":[]},{"name":"icon-32.png","expanded":true,"children":[]},{"name":"icon-512.png","expanded":true,"children":[]},{"name":"icon-64.png","expanded":true,"children":[]},{"name":"loading-logo.png","expanded":true,"children":[]}]},{"name":"Files","expanded":true,"children":[]}]}]},"propertiesBarActiveObject":{}}