{
	"name": "Fire",
	"plugin-id": "Sprite",
	"sid": 10406022031328,
	"isGlobal": false,
	"instanceVariables": [],
	"behaviorTypes": [],
	"effectTypes": [],
	"animations": {
		"items": [
			{
				"frames": [
					{
						"width": 376,
						"height": 522,
						"originX": 0.5,
						"originY": 0.881226,
						"originalSource": "H:\\ИГРОСТРОЙ\\15-sprite-effects\\normal\\flame\\flame_01.png",
						"exportFormat": "lossless",
						"exportQuality": 0.8,
						"fileType": "image/png",
						"imageSpriteId": 8402393,
						"useCollisionPoly": true,
						"duration": 1,
						"tag": ""
					},
					{
						"width": 376,
						"height": 522,
						"originX": 0.5,
						"originY": 0.881226,
						"originalSource": "H:\\ИГРОСТРОЙ\\15-sprite-effects\\normal\\flame\\flame_02.png",
						"exportFormat": "lossless",
						"exportQuality": 0.8,
						"fileType": "image/png",
						"imageSpriteId": 7721754,
						"useCollisionPoly": true,
						"duration": 1,
						"tag": ""
					},
					{
						"width": 376,
						"height": 522,
						"originX": 0.5,
						"originY": 0.881226,
						"originalSource": "H:\\ИГРОСТРОЙ\\15-sprite-effects\\normal\\flame\\flame_03.png",
						"exportFormat": "lossless",
						"exportQuality": 0.8,
						"fileType": "image/png",
						"imageSpriteId": 9441054,
						"useCollisionPoly": true,
						"duration": 1,
						"tag": ""
					},
					{
						"width": 376,
						"height": 522,
						"originX": 0.5,
						"originY": 0.881226,
						"originalSource": "H:\\ИГРОСТРОЙ\\15-sprite-effects\\normal\\flame\\flame_04.png",
						"exportFormat": "lossless",
						"exportQuality": 0.8,
						"fileType": "image/png",
						"imageSpriteId": 4757196,
						"useCollisionPoly": true,
						"duration": 1,
						"tag": ""
					},
					{
						"width": 376,
						"height": 522,
						"originX": 0.5,
						"originY": 0.881226,
						"originalSource": "H:\\ИГРОСТРОЙ\\15-sprite-effects\\normal\\flame\\flame_05.png",
						"exportFormat": "lossless",
						"exportQuality": 0.8,
						"fileType": "image/png",
						"imageSpriteId": 8375716,
						"useCollisionPoly": true,
						"duration": 1,
						"tag": ""
					},
					{
						"width": 376,
						"height": 522,
						"originX": 0.5,
						"originY": 0.881226,
						"originalSource": "H:\\ИГРОСТРОЙ\\15-sprite-effects\\normal\\flame\\flame_06.png",
						"exportFormat": "lossless",
						"exportQuality": 0.8,
						"fileType": "image/png",
						"imageSpriteId": 1354662,
						"useCollisionPoly": true,
						"duration": 1,
						"tag": ""
					},
					{
						"width": 376,
						"height": 522,
						"originX": 0.5,
						"originY": 0.881226,
						"originalSource": "H:\\ИГРОСТРОЙ\\15-sprite-effects\\normal\\flame\\flame_07.png",
						"exportFormat": "lossless",
						"exportQuality": 0.8,
						"fileType": "image/png",
						"imageSpriteId": 9160007,
						"useCollisionPoly": true,
						"duration": 1,
						"tag": ""
					},
					{
						"width": 376,
						"height": 522,
						"originX": 0.5,
						"originY": 0.881226,
						"originalSource": "H:\\ИГРОСТРОЙ\\15-sprite-effects\\normal\\flame\\flame_08.png",
						"exportFormat": "lossless",
						"exportQuality": 0.8,
						"fileType": "image/png",
						"imageSpriteId": 7724251,
						"useCollisionPoly": true,
						"duration": 1,
						"tag": ""
					},
					{
						"width": 376,
						"height": 522,
						"originX": 0.5,
						"originY": 0.881226,
						"originalSource": "H:\\ИГРОСТРОЙ\\15-sprite-effects\\normal\\flame\\flame_09.png",
						"exportFormat": "lossless",
						"exportQuality": 0.8,
						"fileType": "image/png",
						"imageSpriteId": 7890382,
						"useCollisionPoly": true,
						"duration": 1,
						"tag": ""
					},
					{
						"width": 376,
						"height": 522,
						"originX": 0.5,
						"originY": 0.881226,
						"originalSource": "H:\\ИГРОСТРОЙ\\15-sprite-effects\\normal\\flame\\flame_10.png",
						"exportFormat": "lossless",
						"exportQuality": 0.8,
						"fileType": "image/png",
						"imageSpriteId": 6405875,
						"useCollisionPoly": true,
						"duration": 1,
						"tag": ""
					},
					{
						"width": 376,
						"height": 522,
						"originX": 0.5,
						"originY": 0.881226,
						"originalSource": "H:\\ИГРОСТРОЙ\\15-sprite-effects\\normal\\flame\\flame_11.png",
						"exportFormat": "lossless",
						"exportQuality": 0.8,
						"fileType": "image/png",
						"imageSpriteId": 9136709,
						"useCollisionPoly": true,
						"duration": 1,
						"tag": ""
					},
					{
						"width": 376,
						"height": 522,
						"originX": 0.5,
						"originY": 0.881226,
						"originalSource": "H:\\ИГРОСТРОЙ\\15-sprite-effects\\normal\\flame\\flame_12.png",
						"exportFormat": "lossless",
						"exportQuality": 0.8,
						"fileType": "image/png",
						"imageSpriteId": 4703314,
						"useCollisionPoly": true,
						"duration": 1,
						"tag": ""
					},
					{
						"width": 376,
						"height": 522,
						"originX": 0.5,
						"originY": 0.881226,
						"originalSource": "H:\\ИГРОСТРОЙ\\15-sprite-effects\\normal\\flame\\flame_13.png",
						"exportFormat": "lossless",
						"exportQuality": 0.8,
						"fileType": "image/png",
						"imageSpriteId": 4249914,
						"useCollisionPoly": true,
						"duration": 1,
						"tag": ""
					},
					{
						"width": 376,
						"height": 522,
						"originX": 0.5,
						"originY": 0.881226,
						"originalSource": "H:\\ИГРОСТРОЙ\\15-sprite-effects\\normal\\flame\\flame_14.png",
						"exportFormat": "lossless",
						"exportQuality": 0.8,
						"fileType": "image/png",
						"imageSpriteId": 5867916,
						"useCollisionPoly": true,
						"duration": 1,
						"tag": ""
					},
					{
						"width": 376,
						"height": 522,
						"originX": 0.5,
						"originY": 0.881226,
						"originalSource": "H:\\ИГРОСТРОЙ\\15-sprite-effects\\normal\\flame\\flame_15.png",
						"exportFormat": "lossless",
						"exportQuality": 0.8,
						"fileType": "image/png",
						"imageSpriteId": 1808054,
						"useCollisionPoly": true,
						"duration": 1,
						"tag": ""
					},
					{
						"width": 376,
						"height": 522,
						"originX": 0.5,
						"originY": 0.881226,
						"originalSource": "H:\\ИГРОСТРОЙ\\15-sprite-effects\\normal\\flame\\flame_16.png",
						"exportFormat": "lossless",
						"exportQuality": 0.8,
						"fileType": "image/png",
						"imageSpriteId": 7052379,
						"useCollisionPoly": true,
						"duration": 1,
						"tag": ""
					},
					{
						"width": 376,
						"height": 522,
						"originX": 0.5,
						"originY": 0.881226,
						"originalSource": "H:\\ИГРОСТРОЙ\\15-sprite-effects\\normal\\flame\\flame_17.png",
						"exportFormat": "lossless",
						"exportQuality": 0.8,
						"fileType": "image/png",
						"imageSpriteId": 5007840,
						"useCollisionPoly": true,
						"duration": 1,
						"tag": ""
					},
					{
						"width": 376,
						"height": 522,
						"originX": 0.5,
						"originY": 0.881226,
						"originalSource": "H:\\ИГРОСТРОЙ\\15-sprite-effects\\normal\\flame\\flame_18.png",
						"exportFormat": "lossless",
						"exportQuality": 0.8,
						"fileType": "image/png",
						"imageSpriteId": 445777,
						"useCollisionPoly": true,
						"duration": 1,
						"tag": ""
					},
					{
						"width": 376,
						"height": 522,
						"originX": 0.5,
						"originY": 0.881226,
						"originalSource": "H:\\ИГРОСТРОЙ\\15-sprite-effects\\normal\\flame\\flame_19.png",
						"exportFormat": "lossless",
						"exportQuality": 0.8,
						"fileType": "image/png",
						"imageSpriteId": 6058981,
						"useCollisionPoly": true,
						"duration": 1,
						"tag": ""
					},
					{
						"width": 376,
						"height": 522,
						"originX": 0.5,
						"originY": 0.881226,
						"originalSource": "H:\\ИГРОСТРОЙ\\15-sprite-effects\\normal\\flame\\flame_20.png",
						"exportFormat": "lossless",
						"exportQuality": 0.8,
						"fileType": "image/png",
						"imageSpriteId": 4151427,
						"useCollisionPoly": true,
						"duration": 1,
						"tag": ""
					},
					{
						"width": 376,
						"height": 522,
						"originX": 0.5,
						"originY": 0.881226,
						"originalSource": "H:\\ИГРОСТРОЙ\\15-sprite-effects\\normal\\flame\\flame_21.png",
						"exportFormat": "lossless",
						"exportQuality": 0.8,
						"fileType": "image/png",
						"imageSpriteId": 6277267,
						"useCollisionPoly": true,
						"duration": 1,
						"tag": ""
					},
					{
						"width": 376,
						"height": 522,
						"originX": 0.5,
						"originY": 0.881226,
						"originalSource": "H:\\ИГРОСТРОЙ\\15-sprite-effects\\normal\\flame\\flame_22.png",
						"exportFormat": "lossless",
						"exportQuality": 0.8,
						"fileType": "image/png",
						"imageSpriteId": 4193608,
						"useCollisionPoly": true,
						"duration": 1,
						"tag": ""
					},
					{
						"width": 376,
						"height": 522,
						"originX": 0.5,
						"originY": 0.881226,
						"originalSource": "H:\\ИГРОСТРОЙ\\15-sprite-effects\\normal\\flame\\flame_23.png",
						"exportFormat": "lossless",
						"exportQuality": 0.8,
						"fileType": "image/png",
						"imageSpriteId": 9307829,
						"useCollisionPoly": true,
						"duration": 1,
						"tag": ""
					},
					{
						"width": 376,
						"height": 522,
						"originX": 0.5,
						"originY": 0.881226,
						"originalSource": "H:\\ИГРОСТРОЙ\\15-sprite-effects\\normal\\flame\\flame_24.png",
						"exportFormat": "lossless",
						"exportQuality": 0.8,
						"fileType": "image/png",
						"imageSpriteId": 7796233,
						"useCollisionPoly": true,
						"duration": 1,
						"tag": ""
					},
					{
						"width": 376,
						"height": 522,
						"originX": 0.5,
						"originY": 0.881226,
						"originalSource": "H:\\ИГРОСТРОЙ\\15-sprite-effects\\normal\\flame\\flame_25.png",
						"exportFormat": "lossless",
						"exportQuality": 0.8,
						"fileType": "image/png",
						"imageSpriteId": 414410,
						"useCollisionPoly": true,
						"duration": 1,
						"tag": ""
					},
					{
						"width": 376,
						"height": 522,
						"originX": 0.5,
						"originY": 0.881226,
						"originalSource": "H:\\ИГРОСТРОЙ\\15-sprite-effects\\normal\\flame\\flame_26.png",
						"exportFormat": "lossless",
						"exportQuality": 0.8,
						"fileType": "image/png",
						"imageSpriteId": 7067071,
						"useCollisionPoly": true,
						"duration": 1,
						"tag": ""
					},
					{
						"width": 376,
						"height": 522,
						"originX": 0.5,
						"originY": 0.881226,
						"originalSource": "H:\\ИГРОСТРОЙ\\15-sprite-effects\\normal\\flame\\flame_27.png",
						"exportFormat": "lossless",
						"exportQuality": 0.8,
						"fileType": "image/png",
						"imageSpriteId": 1569512,
						"useCollisionPoly": true,
						"duration": 1,
						"tag": ""
					},
					{
						"width": 376,
						"height": 522,
						"originX": 0.5,
						"originY": 0.881226,
						"originalSource": "H:\\ИГРОСТРОЙ\\15-sprite-effects\\normal\\flame\\flame_28.png",
						"exportFormat": "lossless",
						"exportQuality": 0.8,
						"fileType": "image/png",
						"imageSpriteId": 8175927,
						"useCollisionPoly": true,
						"duration": 1,
						"tag": ""
					},
					{
						"width": 376,
						"height": 522,
						"originX": 0.5,
						"originY": 0.881226,
						"originalSource": "H:\\ИГРОСТРОЙ\\15-sprite-effects\\normal\\flame\\flame_29.png",
						"exportFormat": "lossless",
						"exportQuality": 0.8,
						"fileType": "image/png",
						"imageSpriteId": 8856133,
						"useCollisionPoly": true,
						"duration": 1,
						"tag": ""
					},
					{
						"width": 376,
						"height": 522,
						"originX": 0.5,
						"originY": 0.881226,
						"originalSource": "H:\\ИГРОСТРОЙ\\15-sprite-effects\\normal\\flame\\flame_30.png",
						"exportFormat": "lossless",
						"exportQuality": 0.8,
						"fileType": "image/png",
						"imageSpriteId": 3416786,
						"useCollisionPoly": true,
						"duration": 1,
						"tag": ""
					},
					{
						"width": 376,
						"height": 522,
						"originX": 0.5,
						"originY": 0.881226,
						"originalSource": "H:\\ИГРОСТРОЙ\\15-sprite-effects\\normal\\flame\\flame_31.png",
						"exportFormat": "lossless",
						"exportQuality": 0.8,
						"fileType": "image/png",
						"imageSpriteId": 4797448,
						"useCollisionPoly": true,
						"duration": 1,
						"tag": ""
					},
					{
						"width": 376,
						"height": 522,
						"originX": 0.5,
						"originY": 0.881226,
						"originalSource": "H:\\ИГРОСТРОЙ\\15-sprite-effects\\normal\\flame\\flame_32.png",
						"exportFormat": "lossless",
						"exportQuality": 0.8,
						"fileType": "image/png",
						"imageSpriteId": 7489071,
						"useCollisionPoly": true,
						"duration": 1,
						"tag": ""
					},
					{
						"width": 376,
						"height": 522,
						"originX": 0.5,
						"originY": 0.881226,
						"originalSource": "H:\\ИГРОСТРОЙ\\15-sprite-effects\\normal\\flame\\flame_33.png",
						"exportFormat": "lossless",
						"exportQuality": 0.8,
						"fileType": "image/png",
						"imageSpriteId": 3934618,
						"useCollisionPoly": true,
						"duration": 1,
						"tag": ""
					},
					{
						"width": 376,
						"height": 522,
						"originX": 0.5,
						"originY": 0.881226,
						"originalSource": "H:\\ИГРОСТРОЙ\\15-sprite-effects\\normal\\flame\\flame_34.png",
						"exportFormat": "lossless",
						"exportQuality": 0.8,
						"fileType": "image/png",
						"imageSpriteId": 7118031,
						"useCollisionPoly": true,
						"duration": 1,
						"tag": ""
					},
					{
						"width": 376,
						"height": 522,
						"originX": 0.5,
						"originY": 0.881226,
						"originalSource": "H:\\ИГРОСТРОЙ\\15-sprite-effects\\normal\\flame\\flame_35.png",
						"exportFormat": "lossless",
						"exportQuality": 0.8,
						"fileType": "image/png",
						"imageSpriteId": 7426705,
						"useCollisionPoly": true,
						"duration": 1,
						"tag": ""
					},
					{
						"width": 376,
						"height": 522,
						"originX": 0.5,
						"originY": 0.881226,
						"originalSource": "H:\\ИГРОСТРОЙ\\15-sprite-effects\\normal\\flame\\flame_36.png",
						"exportFormat": "lossless",
						"exportQuality": 0.8,
						"fileType": "image/png",
						"imageSpriteId": 9631558,
						"useCollisionPoly": true,
						"duration": 1,
						"tag": ""
					},
					{
						"width": 376,
						"height": 522,
						"originX": 0.5,
						"originY": 0.881226,
						"originalSource": "H:\\ИГРОСТРОЙ\\15-sprite-effects\\normal\\flame\\flame_37.png",
						"exportFormat": "lossless",
						"exportQuality": 0.8,
						"fileType": "image/png",
						"imageSpriteId": 8733969,
						"useCollisionPoly": true,
						"duration": 1,
						"tag": ""
					},
					{
						"width": 376,
						"height": 522,
						"originX": 0.5,
						"originY": 0.881226,
						"originalSource": "H:\\ИГРОСТРОЙ\\15-sprite-effects\\normal\\flame\\flame_38.png",
						"exportFormat": "lossless",
						"exportQuality": 0.8,
						"fileType": "image/png",
						"imageSpriteId": 2440857,
						"useCollisionPoly": true,
						"duration": 1,
						"tag": ""
					},
					{
						"width": 376,
						"height": 522,
						"originX": 0.5,
						"originY": 0.881226,
						"originalSource": "H:\\ИГРОСТРОЙ\\15-sprite-effects\\normal\\flame\\flame_39.png",
						"exportFormat": "lossless",
						"exportQuality": 0.8,
						"fileType": "image/png",
						"imageSpriteId": 7775370,
						"useCollisionPoly": true,
						"duration": 1,
						"tag": ""
					},
					{
						"width": 376,
						"height": 522,
						"originX": 0.5,
						"originY": 0.881226,
						"originalSource": "H:\\ИГРОСТРОЙ\\15-sprite-effects\\normal\\flame\\flame_40.png",
						"exportFormat": "lossless",
						"exportQuality": 0.8,
						"fileType": "image/png",
						"imageSpriteId": 5123595,
						"useCollisionPoly": true,
						"duration": 1,
						"tag": ""
					},
					{
						"width": 376,
						"height": 522,
						"originX": 0.5,
						"originY": 0.881226,
						"originalSource": "H:\\ИГРОСТРОЙ\\15-sprite-effects\\normal\\flame\\flame_41.png",
						"exportFormat": "lossless",
						"exportQuality": 0.8,
						"fileType": "image/png",
						"imageSpriteId": 3592057,
						"useCollisionPoly": true,
						"duration": 1,
						"tag": ""
					},
					{
						"width": 376,
						"height": 522,
						"originX": 0.5,
						"originY": 0.881226,
						"originalSource": "H:\\ИГРОСТРОЙ\\15-sprite-effects\\normal\\flame\\flame_42.png",
						"exportFormat": "lossless",
						"exportQuality": 0.8,
						"fileType": "image/png",
						"imageSpriteId": 2418302,
						"useCollisionPoly": true,
						"duration": 1,
						"tag": ""
					},
					{
						"width": 376,
						"height": 522,
						"originX": 0.5,
						"originY": 0.881226,
						"originalSource": "H:\\ИГРОСТРОЙ\\15-sprite-effects\\normal\\flame\\flame_43.png",
						"exportFormat": "lossless",
						"exportQuality": 0.8,
						"fileType": "image/png",
						"imageSpriteId": 2052698,
						"useCollisionPoly": true,
						"duration": 1,
						"tag": ""
					},
					{
						"width": 376,
						"height": 522,
						"originX": 0.5,
						"originY": 0.881226,
						"originalSource": "H:\\ИГРОСТРОЙ\\15-sprite-effects\\normal\\flame\\flame_44.png",
						"exportFormat": "lossless",
						"exportQuality": 0.8,
						"fileType": "image/png",
						"imageSpriteId": 4470228,
						"useCollisionPoly": true,
						"duration": 1,
						"tag": ""
					},
					{
						"width": 376,
						"height": 522,
						"originX": 0.5,
						"originY": 0.881226,
						"originalSource": "H:\\ИГРОСТРОЙ\\15-sprite-effects\\normal\\flame\\flame_45.png",
						"exportFormat": "lossless",
						"exportQuality": 0.8,
						"fileType": "image/png",
						"imageSpriteId": 1968786,
						"useCollisionPoly": true,
						"duration": 1,
						"tag": ""
					},
					{
						"width": 376,
						"height": 522,
						"originX": 0.5,
						"originY": 0.881226,
						"originalSource": "H:\\ИГРОСТРОЙ\\15-sprite-effects\\normal\\flame\\flame_46.png",
						"exportFormat": "lossless",
						"exportQuality": 0.8,
						"fileType": "image/png",
						"imageSpriteId": 167821,
						"useCollisionPoly": true,
						"duration": 1,
						"tag": ""
					},
					{
						"width": 376,
						"height": 522,
						"originX": 0.5,
						"originY": 0.881226,
						"originalSource": "H:\\ИГРОСТРОЙ\\15-sprite-effects\\normal\\flame\\flame_47.png",
						"exportFormat": "lossless",
						"exportQuality": 0.8,
						"fileType": "image/png",
						"imageSpriteId": 5177086,
						"useCollisionPoly": true,
						"duration": 1,
						"tag": ""
					},
					{
						"width": 376,
						"height": 522,
						"originX": 0.5,
						"originY": 0.881226,
						"originalSource": "H:\\ИГРОСТРОЙ\\15-sprite-effects\\normal\\flame\\flame_48.png",
						"exportFormat": "lossless",
						"exportQuality": 0.8,
						"fileType": "image/png",
						"imageSpriteId": 4155999,
						"useCollisionPoly": true,
						"duration": 1,
						"tag": ""
					},
					{
						"width": 376,
						"height": 522,
						"originX": 0.5,
						"originY": 0.881226,
						"originalSource": "H:\\ИГРОСТРОЙ\\15-sprite-effects\\normal\\flame\\flame_49.png",
						"exportFormat": "lossless",
						"exportQuality": 0.8,
						"fileType": "image/png",
						"imageSpriteId": 7200611,
						"useCollisionPoly": true,
						"duration": 1,
						"tag": ""
					},
					{
						"width": 376,
						"height": 522,
						"originX": 0.5,
						"originY": 0.881226,
						"originalSource": "H:\\ИГРОСТРОЙ\\15-sprite-effects\\normal\\flame\\flame_50.png",
						"exportFormat": "lossless",
						"exportQuality": 0.8,
						"fileType": "image/png",
						"imageSpriteId": 4149498,
						"useCollisionPoly": true,
						"duration": 1,
						"tag": ""
					},
					{
						"width": 376,
						"height": 522,
						"originX": 0.5,
						"originY": 0.881226,
						"originalSource": "H:\\ИГРОСТРОЙ\\15-sprite-effects\\normal\\flame\\flame_51.png",
						"exportFormat": "lossless",
						"exportQuality": 0.8,
						"fileType": "image/png",
						"imageSpriteId": 9905995,
						"useCollisionPoly": true,
						"duration": 1,
						"tag": ""
					}
				],
				"sid": 2159841182220982,
				"name": "Default",
				"isLooping": true,
				"isPingPong": false,
				"repeatCount": 1,
				"repeatTo": 0,
				"speed": 24
			}
		],
		"subfolders": []
	}
}